remind_task/__init__.py
remind_task/remindtask.py
remind_task/tasks.yml
remind_task-0.2.0.dist-info/entry_points.txt
remind_task-0.2.0.dist-info/WHEEL
remind_task-0.2.0.dist-info/METADATA
remind_task-0.2.0.dist-info/RECORD
