Metadata-Version: 2.1
Name: remind-task
Version: 0.2.0
Summary: 
Home-page: https://github.com/atu4403/remind_task
License: MIT
Author: atu4403
Author-email: 73111778+atu4403@users.noreply.github.com
Requires-Python: >=3.8,<4.0
Classifier: License :: OSI Approved :: MIT License
Classifier: Programming Language :: Python :: 3
Classifier: Programming Language :: Python :: 3.8
Classifier: Programming Language :: Python :: 3.9
Requires-Dist: PyYAML (>=5.3.1,<6.0.0)
Requires-Dist: fire (>=0.3.1,<0.4.0)
Project-URL: Repository, https://github.com/atu4403/remind_task
